grapa/__init__.py
grapa/constants.py
grapa/functionals.py
psorus-0.1.dist-info/LICENSE
psorus-0.1.dist-info/METADATA
psorus-0.1.dist-info/WHEEL
psorus-0.1.dist-info/top_level.txt
psorus-0.1.dist-info/RECORD
