Metadata-Version: 2.1
Name: psorus
Version: 0.1
Summary: A Graph Autoencoder Library for tensorflow and keras
Home-page: https://github.com/psorus/grapa/
Author: Simon Klüttermann
Author-email: Simon.Kluettermann@gmx.de
License: UNKNOWN
Platform: UNKNOWN
Classifier: Programming Language :: Python :: 3
Classifier: License :: OSI Approved :: MIT License
Classifier: Operating System :: OS Independent
Requires-Python: >=3.6
